setup.py
distributions8/Binomialdistribution.py
distributions8/Gaussiandistribution.py
distributions8/Generaldistribution.py
distributions8/__init__.py
distributions8.egg-info/PKG-INFO
distributions8.egg-info/SOURCES.txt
distributions8.egg-info/dependency_links.txt
distributions8.egg-info/not-zip-safe
distributions8.egg-info/top_level.txt